yamlfix-1.19.0.dist-info/METADATA
yamlfix-1.19.0.dist-info/WHEEL
yamlfix-1.19.0.dist-info/entry_points.txt
yamlfix-1.19.0.dist-info/licenses/LICENSE
yamlfix/__init__.py
yamlfix/adapters.py
yamlfix/config.py
yamlfix/entrypoints/__init__.py
yamlfix/entrypoints/cli.py
yamlfix/model.py
yamlfix/py.typed
yamlfix/services.py
yamlfix/version.py
yamlfix-1.19.0.dist-info/RECORD
