Metadata-Version: 2.1
Name: yamlfix
Version: 1.19.0
Summary: A simple opionated yaml formatter that keeps your comments!
Author-Email: Lyz <lyz-code-security-advisories@riseup.net>
License: GPL-3.0-only
Classifier: Development Status :: 5 - Production/Stable
Classifier: Intended Audience :: Developers
Classifier: License :: OSI Approved :: GNU General Public License v3 (GPLv3)
Classifier: Operating System :: Unix
Classifier: Operating System :: POSIX
Classifier: Programming Language :: Python
Classifier: Programming Language :: Python :: 3
Classifier: Programming Language :: Python :: 3.9
Classifier: Programming Language :: Python :: 3.10
Classifier: Programming Language :: Python :: 3.11
Classifier: Topic :: Utilities
Classifier: Natural Language :: English
Project-URL: Issues, https://github.com/lyz-code/yamlfix/issues
Project-URL: homepage, https://github.com/lyz-code/yamlfix
Project-URL: documentation, https://lyz-code.github.io/yamlfix
Requires-Python: >=3.9.1
Requires-Dist: click>=8.1.3
Requires-Dist: ruyaml>=0.91.0
Requires-Dist: maison>=2.0.0
Requires-Dist: pydantic>=2.8.2
